EMCqMRI/__init__.py
EMCqMRI/core/__init__.py
EMCqMRI/core/base/__init__.py
EMCqMRI/core/base/base_dataset.py
EMCqMRI/core/base/base_inference_model.py
EMCqMRI/core/base/base_likelihood_model.py
EMCqMRI/core/base/base_signal_model.py
EMCqMRI/core/engine/__init__.py
EMCqMRI/core/engine/build_model.py
EMCqMRI/core/engine/data_loader.py
EMCqMRI/core/engine/estimate.py
EMCqMRI/core/engine/train_model.py
EMCqMRI/core/models/__init__.py
EMCqMRI/core/models/dataset/__init__.py
EMCqMRI/core/models/dataset/base.py
EMCqMRI/core/models/inference/__init__.py
EMCqMRI/core/models/inference/mle.py
EMCqMRI/core/models/inference/resnet.py
EMCqMRI/core/models/inference/rim.py
EMCqMRI/core/models/inference/rnn.py
EMCqMRI/core/models/likelihood/__init__.py
EMCqMRI/core/models/likelihood/gaussian.py
EMCqMRI/core/models/signal/__init__.py
EMCqMRI/core/models/signal/fse.py
EMCqMRI/core/models/signal/looklocker.py
EMCqMRI/core/utilities/__init__.py
EMCqMRI/core/utilities/checkpoint_utilities.py
EMCqMRI/core/utilities/configuration_utilities.py
EMCqMRI/core/utilities/core_utilities.py
EMCqMRI/core/utilities/dataset_utilities.py
EMCqMRI/core/utilities/image_utilities.py
EMCqMRI/core/utilities/torch_utils.py
EMCqMRI-1.1.17.dist-info/LICENSE
EMCqMRI-1.1.17.dist-info/METADATA
EMCqMRI-1.1.17.dist-info/WHEEL
EMCqMRI-1.1.17.dist-info/top_level.txt
EMCqMRI-1.1.17.dist-info/RECORD
