Metadata-Version: 2.1
Name: EMCqMRI
Version: 1.1.17
Summary: A distribution of a general tool for training and inference of QMRI models
Home-page: https://gitlab.com/e.ribeirosabidussi/emcqmri
Author: Emanoel R. Sabidussi
Author-email: e.ribeirosabidussi@erasmusmc.nl
Classifier: Programming Language :: Python :: 3
Classifier: License :: OSI Approved :: MIT License
Classifier: Operating System :: OS Independent
License-File: LICENSE
Requires-Dist: h5py
Requires-Dist: numpy >=1.19.0
Requires-Dist: scipy >=1.2.1
Requires-Dist: matplotlib >=3.3.2
Requires-Dist: PyQt5 >=5.15.1
Requires-Dist: progress >=1.5
Requires-Dist: monai
Requires-Dist: pytorch-ignite
Requires-Dist: pillow
Requires-Dist: dipy ==1.7.0
Requires-Dist: fury ==0.9.0
Requires-Dist: tensorboard
